bioio_dv/__init__.py
bioio_dv/py.typed
bioio_dv/reader.py
bioio_dv/reader_metadata.py
bioio_dv/tests/__init__.py
bioio_dv/tests/conftest.py
bioio_dv/tests/test_reader.py
bioio_dv-1.2.0.dist-info/licenses/LICENSE
scripts/TEST_RESOURCES_HASH.txt
scripts/download_test_resources.py
scripts/upload_test_resources.py
bioio_dv-1.2.0.dist-info/METADATA
bioio_dv-1.2.0.dist-info/WHEEL
bioio_dv-1.2.0.dist-info/entry_points.txt
bioio_dv-1.2.0.dist-info/top_level.txt
bioio_dv-1.2.0.dist-info/RECORD
