Metadata-Version: 2.4
Name: bioio-dv
Version: 1.2.0
Summary: A BioIO reader plugin for reading Digital Video (DV) files.
Author-email: bioio-devs <brian.whitney@alleninstitute.org>
License: MIT License
Project-URL: Homepage, https://github.com/bioio-devs/bioio-dv
Project-URL: Bug Tracker, https://github.com/bioio-devs/bioio-dv/issues
Project-URL: Documentation, https://bioio-devs.github.io/bioio-dv
Project-URL: User Support, https://github.com/bioio-devs/bioio-dv/issues
Classifier: Development Status :: 4 - Beta
Classifier: Natural Language :: English
Classifier: Programming Language :: Python :: 3.10
Classifier: Programming Language :: Python :: 3.11
Classifier: Programming Language :: Python :: 3.12
Classifier: Programming Language :: Python :: 3.13
Requires-Python: >=3.10
License-File: LICENSE
Requires-Dist: bioio-base>=0.3.0
Requires-Dist: fsspec>=2022.8.0
Requires-Dist: mrc>=0.2.0
Requires-Dist: resource-backed-dask-array>=0.1.0
Requires-Dist: xarray>=0.16.1
Provides-Extra: lint
Requires-Dist: pre-commit>=2.20.0; extra == "lint"
Provides-Extra: test
Requires-Dist: coverage>=5.1; extra == "test"
Requires-Dist: pytest>=5.4.3; extra == "test"
Requires-Dist: pytest-cov>=2.9.0; extra == "test"
Requires-Dist: pytest-raises>=0.11; extra == "test"
Requires-Dist: quilt3; extra == "test"
Requires-Dist: types-PyYAML>=6.0.12.9; extra == "test"
Dynamic: license-file
